devtools/scripts/create_conda_env.py
docs/conf.py
mdpath/__init__.py
mdpath/_version.py
mdpath/mdpath.py
mdpath/mdpath_tools.py
mdpath/py.typed
mdpath/vis_pymol.py
mdpath/src/__init__.py
mdpath/src/bootstrap.py
mdpath/src/cluster.py
mdpath/src/graph.py
mdpath/src/mutual_information.py
mdpath/src/notebook_vis.py
mdpath/src/structure.py
mdpath/src/visualization.py
mdpath/tests/__init__.py
mdpath/tests/test_bootstrap.py
mdpath/tests/test_cluster.py
mdpath/tests/test_graph.py
mdpath/tests/test_mdpath.py
mdpath/tests/test_mdpath_tools.py
mdpath/tests/test_mutual_information.py
mdpath/tests/test_notebook_vis.py
mdpath/tests/test_structure.py
mdpath/tests/test_visualization.py
mdpath-1.0.2.dist-info/LICENSE
mdpath-1.0.2.dist-info/METADATA
mdpath-1.0.2.dist-info/WHEEL
mdpath-1.0.2.dist-info/entry_points.txt
mdpath-1.0.2.dist-info/top_level.txt
mdpath-1.0.2.dist-info/RECORD
