Metadata-Version: 2.2
Name: mdpath
Version: 1.0.2
Summary: MD signal transduction calculation
Author-email: Niklas Piet Doering and Marvin Taterra <niklas.piet.doering@fu-berlin.de>
License: MIT
Classifier: License :: OSI Approved :: MIT License
Classifier: Programming Language :: Python :: 3
Requires-Python: >=3.10
License-File: LICENSE
Requires-Dist: MDAnalysis>=2.7.0
Requires-Dist: pandas
Requires-Dist: scikit-learn
Requires-Dist: networkx
Requires-Dist: scipy
Requires-Dist: biopython
Requires-Dist: tqdm
Requires-Dist: seaborn
Requires-Dist: nglview
Requires-Dist: pillow
Requires-Dist: numpy-stl
Provides-Extra: test
Requires-Dist: pytest>=6.1.2; extra == "test"
Requires-Dist: pytest-runner; extra == "test"
Requires-Dist: pytest-mock>=3.14.0; extra == "test"
